experimental.catalogplan-1.0.0a4-py3.11-nspkg.pth
experimental/catalogplan/__init__.py
experimental/catalogplan/configure.zcml
experimental/catalogplan/tests/__init__.py
experimental/catalogplan/tests/test_plan.py
experimental_catalogplan-1.0.0a4.dist-info/licenses/LICENSE.txt
experimental_catalogplan-1.0.0a4.dist-info/METADATA
experimental_catalogplan-1.0.0a4.dist-info/WHEEL
experimental_catalogplan-1.0.0a4.dist-info/entry_points.txt
experimental_catalogplan-1.0.0a4.dist-info/namespace_packages.txt
experimental_catalogplan-1.0.0a4.dist-info/top_level.txt
experimental_catalogplan-1.0.0a4.dist-info/RECORD
