Metadata-Version: 2.4
Name: experimental.catalogplan
Version: 1.0.0a4
Summary: Experimental ZCatalog plan
Home-page: https://github.com/mamico/experimental.catalogplan
Author: Mauro Amico
Author-email: mauro.amico@gmail.com
License: BSD
Project-URL: Issue Tracker, https://github.com/mamico/experimental.catalogplan/issues
Project-URL: Sources, https://github.com/mamico/experimental.catalogplan
Keywords: monkeypatch traverse
Classifier: Framework :: Zope2
Classifier: Framework :: Plone
Classifier: Framework :: Plone :: 4.3
Classifier: Framework :: Plone :: 5.0
Classifier: Framework :: Plone :: 5.1
Classifier: Framework :: Plone :: 5.2
Classifier: License :: OSI Approved :: GNU General Public License v2 (GPLv2)
Classifier: Programming Language :: Python
Classifier: Programming Language :: Python :: 2.7
Classifier: Programming Language :: Python :: 3.7
Classifier: Programming Language :: Python :: 3.8
Classifier: Programming Language :: Python :: 3.9
Classifier: Programming Language :: Python :: 3.10
License-File: LICENSE.txt
Requires-Dist: setuptools
Requires-Dist: six
Requires-Dist: Products.ZCatalog>3.0
Provides-Extra: test
Requires-Dist: Products.CMFPlone[test]; extra == "test"
Dynamic: author
Dynamic: author-email
Dynamic: classifier
Dynamic: description
Dynamic: description-content-type
Dynamic: home-page
Dynamic: keywords
Dynamic: license
Dynamic: license-file
Dynamic: project-url
Dynamic: provides-extra
Dynamic: requires-dist
Dynamic: summary
